hipachectl/__init__.py
hipachectl/api.py
hipachectl/main.py
hipachectl/utils.py
hipachectl/version.py
hipachectl-0.3.0.dist-info/DESCRIPTION.rst
hipachectl-0.3.0.dist-info/entry_points.txt
hipachectl-0.3.0.dist-info/METADATA
hipachectl-0.3.0.dist-info/metadata.json
hipachectl-0.3.0.dist-info/RECORD
hipachectl-0.3.0.dist-info/top_level.txt
hipachectl-0.3.0.dist-info/WHEEL
hipachectl-0.3.0.dist-info/zip-safe
