Metadata-Version: 2.0
Name: hipachectl
Version: 0.3.0
Summary: Command Line Tool to Manage hipache
Home-page: https://github.org/prologic/hipachectl
Author: James Mills
Author-email: James Mills, prologic at shortcircuit dot net dot au
License: MIT
Download-URL: http://github.org/prologic/hipachectl/releases/
Keywords: hipache manage docker
Platform: POSIX
Classifier: Development Status :: 3 - Alpha
Classifier: Environment :: Console
Classifier: Intended Audience :: Developers
Classifier: Intended Audience :: System Administrators
Classifier: License :: OSI Approved :: MIT License
Classifier: Natural Language :: English
Classifier: Operating System :: POSIX :: BSD
Classifier: Operating System :: POSIX :: Linux
Classifier: Operating System :: MacOS :: MacOS X
Classifier: Programming Language :: Python :: 2.6
Classifier: Programming Language :: Python :: 2.7
Classifier: Programming Language :: Python :: Implementation :: CPython
Classifier: Programming Language :: Python :: Implementation :: PyPy
Requires-Dist: redis
